{
  "generator-jhipster": {
    "baseName": "jhipster",
    "packageName": "io.variability.jhipster",
    "packageFolder": "io/variability/jhipster",
    "authenticationType": "jwt",
    "hibernateCache": "no",
    "clusteredHttpSession": "clusteredHttpSession:hazelcast",
    "websocket": "false",
    "databaseType": "sql",
    "devDatabaseType": "postgresql",
    "prodDatabaseType": "postgresql",
    "searchEngine": "false",
    "buildTool": "gradle",
    "jwtSecretKey": "d8837e4a671d25456432b55b1e4a99fe0356ed07",
    "applicationType": "monolith",
    "testFrameworks": [
      "cucumber",
      "protractor",
      "gatling"
    ],
    "jhipsterVersion": "4.8.2",
    "clientFramework": "angularX",
    "serviceDiscoveryType": false,
    "installModules": false,
    "useSass": false,
    "messageBroker": "messageBroker:kafka",
    "enableTranslation": true,
    "nativeLanguage": "en",
    "languages": [
      "en",
      "fr"
    ],
    "skipClient": false,
    "skipServer": false,
    "enableSocialSignIn": "enableSocialSignIn :true",
    "enableSwaggerCodegen": "no"
  }
}