{
  "generator-jhipster": {
    "baseName": "jhipster",
    "packageName": "io.variability.jhipster",
    "packageFolder": "io/variability/jhipster",
    "authenticationType": "Oauth2",
    "hibernateCache": "no",
    "clusteredHttpSession": "false",
    "websocket": "websocket:spring-websocket",
    "databaseType": "sql",
    "devDatabaseType": "h2Disk",
    "prodDatabaseType": "mariadb",
    "searchEngine": "false",
    "buildTool": "gradle",
    "applicationType": "monolith",
    "testFrameworks": [
      "gatling",
      "protractor",
      "cucumber"
    ],
    "jhipsterVersion": "4.8.2",
    "clientFramework": "angularX",
    "serviceDiscoveryType": false,
    "installModules": false,
    "useSass": true,
    "messageBroker": "false",
    "enableTranslation": true,
    "nativeLanguage": "en",
    "languages": [
      "en",
      "fr"
    ],
    "skipClient": false,
    "skipServer": false,
    "enableSocialSignIn": "no",
    "enableSwaggerCodegen": "no"
  }
}