{
  "generator-jhipster": {
    "baseName": "jhipster",
    "packageName": "io.variability.jhipster",
    "packageFolder": "io/variability/jhipster",
    "serverPort": "8080",
    "authenticationType": "session",
    "hibernateCache": "ehcache",
    "clusteredHttpSession": "hazelcast",
    "websocket": "spring-websocket",
    "databaseType": "sql",
    "devDatabaseType": "DiskBased",
    "prodDatabaseType": "postgresql",
    "searchEngine": "elasticsearch",
    "buildTool": "gradle",
    "applicationType": "monolith",
    "testFrameworks": [
      "cucumber",
      "protractor",
      "gatling"
    ],
    "jhiPrefix": "jhi",
    "jhipsterVersion": "3.6.1",
    "useSass": false,
    "enableTranslation": true,
    "nativeLanguage": "en",
    "languages": [
      "en",
      "fr"
    ],
    "enableSocialSignIn": false,
    "rememberMeKey": "13e6029734fb9984533b9bb5c511bca6d624c6ed"
  }
}